MANIFEST.in
README.md
requirements.txt
setup.cfg
setup.py
tox.ini
docs/Makefile
docs/conf.py
docs/index.rst
docs/api/modules.rst
docs/api/pyRscript.rst
pyRscript/__init__.py
pyRscript/pyRscript.py
pyRscript.egg-info/PKG-INFO
pyRscript.egg-info/SOURCES.txt
pyRscript.egg-info/dependency_links.txt
pyRscript.egg-info/requires.txt
pyRscript.egg-info/top_level.txt
tests/test_rscript.py