Metadata-Version: 1.1
Name: pyRscript
Version: 0.0.2
Summary: easy tool to use subprocess call Rscript and execute R program.
Home-page: https://github.com/chairco/pyRscript
Author: chairco
Author-email: chairco@gmail.com
License: UNKNOWN
Platform: UNKNOWN
Classifier: Development Status :: 1 - Planning
Classifier: Environment :: Console
Classifier: Intended Audience :: Developers
Classifier: License :: OSI Approved :: MIT License
Classifier: Operating System :: OS Independent
Classifier: Programming Language :: Python :: 3.6
Classifier: Programming Language :: Python :: Implementation :: PyPy
Classifier: Topic :: Documentation
Classifier: Topic :: Software Development :: Libraries :: Python Modules
